LANDrop/__init__.py
LANDrop/__main__.py
LANDrop/aboutdialog.py
LANDrop/crypto.py
LANDrop/discoveryservice.py
LANDrop/filetransferdialog.py
LANDrop/filetransferreceiver.py
LANDrop/filetransfersender.py
LANDrop/filetransferserver.py
LANDrop/filetransfersession.py
LANDrop/main.py
LANDrop/resources.py
LANDrop/selectfilesdialog.py
LANDrop/sendtodialog.py
LANDrop/settings.py
LANDrop/settingsdialog.py
LANDrop/sodium.py
LANDrop/trayicon.py
LANDrop/ui_aboutdialog.py
LANDrop/ui_filetransferdialog.py
LANDrop/ui_selectfilesdialog.py
LANDrop/ui_sendtodialog.py
LANDrop/ui_settingsdialog.py
LANDrop-0.4.0.dist-info/LICENSE
LANDrop-0.4.0.dist-info/LICENSE.icon
LANDrop-0.4.0.dist-info/METADATA
LANDrop-0.4.0.dist-info/WHEEL
LANDrop-0.4.0.dist-info/entry_points.txt
LANDrop-0.4.0.dist-info/top_level.txt
LANDrop-0.4.0.dist-info/RECORD
