Metadata-Version: 2.1
Name: LANDrop
Version: 0.4.0
Summary: LANDrop is a cross-platform tool that you can use to conveniently transfer photos, videos, and other types of files to other devices on the same local network.
Home-page: https://github.com/heiheiyoyo/PyLANDrop
Author: heiheiyoyo
Author-email: 543425864@qq.com
License: BSD-3
Requires-Python: >=3.6
License-File: LICENSE
License-File: LICENSE.icon
Requires-Dist: PyQt5
Requires-Dist: PyNaCl
Requires-Dist: dataclasses ; python_version < "3.7"
